bump_dictionary/__init__.py
bump_dictionary/cli.py
bump_dictionary/logger.py
bump_dictionary/utils.py
bump_dictionary/models/__init__.py
bump_dictionary/models/latest_dictionary_model.py
bump_dictionary/models/legacy_dictionary_model.py
bump_dictionary-0.1.0.dist-info/METADATA
bump_dictionary-0.1.0.dist-info/WHEEL
bump_dictionary-0.1.0.dist-info/entry_points.txt
bump_dictionary-0.1.0.dist-info/licenses/LICENSE
bump_dictionary-0.1.0.dist-info/RECORD
