Metadata-Version: 2.4
Name: bump-dictionary
Version: 0.1.0
Summary: Convert Neurobagel data dictionaries to the latest version of the data dictionary schema.
Author: Neurobagel Developers
Maintainer-email: Sebastian Urchs <sebastian.urchs@mcgill.ca>, Alyssa Dai <alyssa.dai@mcgill.ca>, Arman Jahanpour <arman.jahanpour@mcgill.ca>
License: MIT License
License-File: LICENSE
Classifier: Development Status :: 1 - Planning
Classifier: Intended Audience :: Science/Research
Classifier: License :: OSI Approved :: MIT License
Classifier: Programming Language :: Python :: 3.10
Classifier: Programming Language :: Python :: 3.11
Requires-Python: >=3.10
Requires-Dist: isodate
Requires-Dist: jsonschema
Requires-Dist: pydantic<3,>=2
Requires-Dist: typer
Provides-Extra: dev
Requires-Dist: coverage; extra == 'dev'
Requires-Dist: pre-commit; extra == 'dev'
Requires-Dist: pytest; extra == 'dev'
Provides-Extra: test
Requires-Dist: coverage; extra == 'test'
Requires-Dist: pytest; extra == 'test'
